melody_features
