Metadata-Version: 2.4
Name: melody-features
Version: 1.1.4
Summary: A Python package for computing tonnes of melodic features found in computational musicology literature.
Author-email: David Whyatt <dmw56@cam.ac.uk>, Peter Harrison <pmch2@cam.ac.uk>
License-Expression: MIT
Project-URL: Homepage, https://github.com/dmwhyatt/melody-features
Project-URL: Issues, https://github.com/dmwhyatt/melody-features/issues
Classifier: Programming Language :: Python :: 3
Classifier: Operating System :: MacOS
Classifier: Operating System :: POSIX :: Linux
Requires-Python: >=3.9
License-File: LICENSE-APACHE
License-File: LICENSE-MIT
Requires-Dist: matplotlib
Requires-Dist: mido
Requires-Dist: natsort
Requires-Dist: numpy
Requires-Dist: pandas
Requires-Dist: pretty_midi
Requires-Dist: py2lispIDyOM
Requires-Dist: pytest>=8.0.0
Requires-Dist: pytest-env>=1.1.0
Requires-Dist: pytest-cov>=4.0.0
Requires-Dist: scipy
Requires-Dist: setuptools
Requires-Dist: tenacity
Requires-Dist: tqdm
Requires-Dist: PyYAML
Dynamic: license-file
